{
  "request": {
    "method": "GET",
    "url": "https://epicaccess.templehealth.org/FhirProxyPrd/api/FHIR/R4/.well-known/smart-configuration",
    "headers": { "Accept": "application/json" }
  },
  "response": {
    "status": 200,
    "body": {
      "authorization_endpoint": "https://epicaccess.templehealth.org/FhirProxyPrd/oauth2/authorize",
      "token_endpoint": "https://epicaccess.templehealth.org/FhirProxyPrd/oauth2/token",
      "scopes_supported": [
        "epic.scanning.dmsusername",
        "fhirUser",
        "launch",
        "openid",
        "profile"
      ],
      "response_types_supported": ["code"],
      "code_challenge_methods_supported": ["S256"],
      "capabilities": [
        "launch-ehr",
        "launch-standalone",
        "client-public",
        "client-confidential-symmetric",
        "client-confidential-asymmetric",
        "context-banner",
        "context-style",
        "context-ehr-patient",
        "context-ehr-encounter",
        "context-standalone-patient",
        "permission-offline",
        "permission-patient",
        "permission-user",
        "permission-v1",
        "permission-v2",
        "sso-openid-connect",
        "authorize-post"
      ]
    }
  }
}
